dints/__init__.py
dints/__version__.py
dints/abc.py
dints/exceptions.py
dints/models.py
dints/py.typed
dints/types.py
dints/locks/__init__.py
dints/locks/memcached.py
dints/locks/redis.py
dints/managers/__init__.py
dints/managers/base.py
dints/managers/local.py
dints/managers/rabbitmq.py
dints/managers/redis.py
dints/timeseries/__init__.py
dints/timeseries/local.py
dints/timeseries/redis.py
dints/util/aiohttp/__init__.py
dints/util/aiohttp/auth.py
dints/util/aiohttp/client_reqrep.py
dints/util/aiohttp/flows/__init__.py
dints/util/aiohttp/flows/negotiate.py
dints-0.0.1.dist-info/LICENSE
dints-0.0.1.dist-info/METADATA
dints-0.0.1.dist-info/WHEEL
dints-0.0.1.dist-info/top_level.txt
dints-0.0.1.dist-info/RECORD
